miss_hmm/HMM.py
miss_hmm/SeqSampling.py
miss_hmm/__init__.py
miss_hmm/learn.py
miss_hmm/model.py
miss_hmm/pred.py
miss_hmm-0.3.0.dist-info/LICENSE.txt.txt
miss_hmm-0.3.0.dist-info/METADATA
miss_hmm-0.3.0.dist-info/WHEEL
miss_hmm-0.3.0.dist-info/top_level.txt
miss_hmm-0.3.0.dist-info/RECORD
