Metadata-Version: 2.1
Name: miss-hmm
Version: 0.3.0
Summary: Inference and prediction on hidden Markov model with missing observations
Home-page: https://github.com/lidongrong/miss_hmm
Author: Dongrong Li
Author-email: DongrongLi@link.cuhk.edu.hk
License: MIT
Platform: UNKNOWN
Classifier: License :: OSI Approved :: MIT License
Classifier: Programming Language :: Python
Classifier: Programming Language :: Python :: 3
Classifier: Programming Language :: Python :: 3.6
Classifier: Programming Language :: Python :: Implementation :: CPython
Classifier: Programming Language :: Python :: Implementation :: PyPy
Requires-Python: >=3.6.0
License-File: LICENSE.txt.txt
Requires-Dist: numpy
Requires-Dist: scipy
